{
    "comma": {
        "branch": "master",
        "description": null,
        "homepage": null,
        "owner": "Shopify",
        "repo": "comma",
        "rev": "4a62ec17e20ce0e738a8e5126b4298a73903b468",
        "sha256": "0n5a3rnv9qnnsrl76kpi6dmaxmwj1mpdd2g0b4n1wfimqfaz6gi1",
        "type": "tarball",
        "url": "https://github.com/Shopify/comma/archive/4a62ec17e20ce0e738a8e5126b4298a73903b468.tar.gz",
        "url_template": "https://github.com/<owner>/<repo>/archive/<rev>.tar.gz"
    },
    "neuron": {
        "branch": "master",
        "description": "Future-proof and simple-to-use notes system based on Zettelkasten.",
        "homepage": "https://neuron.zettel.page",
        "owner": "srid",
        "repo": "neuron",
        "rev": "f2d5c921c1f45dbecf0d98a3e41a40cadb770f14",
        "sha256": "14iblvim691r9hs3dfl7pinqxaqwyad5qwg27k3vqm73365xb58w",
        "type": "tarball",
        "url": "https://github.com/srid/neuron/archive/f2d5c921c1f45dbecf0d98a3e41a40cadb770f14.tar.gz",
        "url_template": "https://github.com/<owner>/<repo>/archive/<rev>.tar.gz"
    },
    "niv": {
        "branch": "master",
        "description": "Easy dependency management for Nix projects",
        "homepage": "https://github.com/nmattia/niv",
        "owner": "nmattia",
        "repo": "niv",
        "rev": "ba57d5a29b4e0f2085917010380ef3ddc3cf380f",
        "sha256": "1kpsvc53x821cmjg1khvp1nz7906gczq8mp83664cr15h94sh8i4",
        "type": "tarball",
        "url": "https://github.com/nmattia/niv/archive/ba57d5a29b4e0f2085917010380ef3ddc3cf380f.tar.gz",
        "url_template": "https://github.com/<owner>/<repo>/archive/<rev>.tar.gz"
    },
    "nix-direnv": {
        "branch": "master",
        "description": "A fast, persistent use_nix implementation for direnv [maintainer=@Mic92] ",
        "homepage": "",
        "owner": "nix-community",
        "repo": "nix-direnv",
        "rev": "a5d469806c300bff5dbf8def8d70925834080157",
        "sha256": "1fn242zgyy54csd8kisgld7qpf2dyajmqfq8100gbrvkxfqqcv2y",
        "type": "tarball",
        "url": "https://github.com/nix-community/nix-direnv/archive/a5d469806c300bff5dbf8def8d70925834080157.tar.gz",
        "url_template": "https://github.com/<owner>/<repo>/archive/<rev>.tar.gz"
    },
    "nixpkgs": {
        "branch": "nixpkgs-unstable",
        "description": "Nix Packages collection",
        "homepage": null,
        "owner": "NixOs",
        "repo": "nixpkgs",
        "rev": "bea44d5ebe332260aa34a1bd48250b6364527356",
        "sha256": "14sfk04iyvyh3jl1s2wayw1y077dwpk2d712nhjk1wwfjkdq03r3",
        "type": "tarball",
        "url": "https://github.com/NixOs/nixpkgs/archive/bea44d5ebe332260aa34a1bd48250b6364527356.tar.gz",
        "url_template": "https://github.com/<owner>/<repo>/archive/<rev>.tar.gz"
    },
    "pre-commit-hooks": {
        "branch": "master",
        "description": "Seamless integration of https://pre-commit.com git hooks with Nix.",
        "homepage": "",
        "owner": "cachix",
        "repo": "pre-commit-hooks.nix",
        "rev": "7a2bec0576d2b7a91e2bbf0ad31e80f08a0b7af3",
        "sha256": "1kn2s1hg93b2czm4wvqn4ya6szv7va61aqwyw3rg2sagr4z41i4h",
        "type": "tarball",
        "url": "https://github.com/cachix/pre-commit-hooks.nix/archive/7a2bec0576d2b7a91e2bbf0ad31e80f08a0b7af3.tar.gz",
        "url_template": "https://github.com/<owner>/<repo>/archive/<rev>.tar.gz"
    }
}
